Metadata-Version: 2.1
Name: workpathapi
Version: 1.0.0
Summary: Package to interact with workpath API
Home-page: https://github.com/dataatelier/workpath-python
Author: Daniel Hafner
Author-email: daniel-hafner1@gmx.de
License: UNKNOWN
Platform: UNKNOWN
Classifier: Programming Language :: Python :: 2.7
Classifier: Programming Language :: Python :: 3.5
Classifier: Programming Language :: Python :: 3.6
Classifier: Programming Language :: Python :: 3.7
Classifier: Programming Language :: Python :: 3.8
Classifier: License :: OSI Approved :: MIT License
Classifier: Operating System :: OS Independent
Requires-Python: >=2.7
